sqlmodel_zod/__init__.py
sqlmodel_zod/cli.py
sqlmodel_zod-0.1.2.dist-info/licenses/LICENSE
sqlmodel_zod-0.1.2.dist-info/METADATA
sqlmodel_zod-0.1.2.dist-info/WHEEL
sqlmodel_zod-0.1.2.dist-info/entry_points.txt
sqlmodel_zod-0.1.2.dist-info/top_level.txt
sqlmodel_zod-0.1.2.dist-info/RECORD
