Metadata-Version: 2.4
Name: sqlmodel-zod
Version: 0.1.2
Summary: A CLI tool to generate Zod schemas from SQLModel models
Author-email: OSS Mafia <dev@oss-mafia.com>
Maintainer-email: Matt Nick <matt@oss-mafia.com>, Adam Smith <adam@oss-mafia.com>
License: MIT License
Project-URL: Homepage, https://github.com/OSSMafia/sqlmodel-zod-generator
Project-URL: Source, https://github.com/OSSMafia/sqlmodel-zod-generator
Keywords: sqlmodel,zod,pydantic,cli,sqlalchemy
Classifier: Development Status :: 5 - Production/Stable
Classifier: Framework :: FastAPI
Classifier: Intended Audience :: Developers
Classifier: License :: OSI Approved :: MIT License
Classifier: Programming Language :: Python :: 3.9
Classifier: Programming Language :: Python :: 3.10
Classifier: Programming Language :: Python :: 3.11
Classifier: Programming Language :: Python :: 3.12
Requires-Python: >=3.9
License-File: LICENSE
Dynamic: license-file
